dataskakare/Europeana.py
dataskakare/GoogleTranslate.py
dataskakare/GoogleVision.py
dataskakare/__init__.py
dataskakare/data_transformation.py
dataskakare-0.2.0.dist-info/LICENSE
dataskakare-0.2.0.dist-info/METADATA
dataskakare-0.2.0.dist-info/WHEEL
dataskakare-0.2.0.dist-info/top_level.txt
dataskakare-0.2.0.dist-info/RECORD
